{
 "0xadd9af0d": "Global/Jump.wav",
 "0x7c3beffd": "Global/Ring.wav",
 "0xf7bc71a3": "Global/StarPost.wav",
 "0x4dedd19b": "Global/LoseRings.wav",
 "0xb6548a9e": "Global/Spring.wav",
 "0x4e4ec6ad": "Global/Destroy.wav",
 "0x6f31866e": "Global/BlueShield.wav",
 "0xc98dace": "Global/BubbleShield.wav",
 "0x1380cb48": "Global/FireShield.wav",
 "0x2c1a12e0": "Global/LightningShield.wav",
 "0xa1cf11fe": "Global/Skidding.wav",
 "0x93cca715": "Global/Charge.wav",
 "0xbdc39486": "Global/Release.wav",
 "0xa310a58": "Global/DropDash.wav",
 "0x57b0d4f4": "Global/Hurt.wav",
 "0xe7aef672": "Global/Roll.wav",
 "0x2a0bfce4": "Global/SignPost.wav",
 "0x973bc66": "Global/SignPost2p.wav",
 "0x6e0fead1": "Global/InstaShield.wav",
 "0xa3ed72e9": "Global/FireDash.wav",
 "0x40d88341": "Global/BubbleBounce.wav",
 "0x7d86f9d": "Global/LightningJump.wav",
 "0xc8a20589": "Global/SpikesMove.wav",
 "0xd9614d78": "Global/Slide.wav",
 "0x13b25149": "Global/Twinkle.wav",
 "0xe9a1ea6": "Global/ScoreAdd.wav",
 "0x26c555a5": "Global/ScoreTotal.wav",
 "0x68ea0c22": "Global/MenuBleep.wav",
 "0xda51157c": "Global/MenuAccept.wav",
 "0xfd0c1a6e": "Global/OuttaHere.wav",
 "0x30011739": "Global/Grab.wav",
 "0x79b1aedc": "Global/Flying.wav",
 "0x8e2140a1": "Global/Tired.wav",
 "0xdf454e8": "Global/Land.wav",
 "0xc16d6f9c": "Global/SpecialRing.wav",
 "0xd4c0617a": "Global/SpecialWarp.wav",
 "0xe4172a6e": "Global/Teleport.wav",
 "0xfd4ca589": "Global/PeelCharge.wav",
 "0xee05779a": "Global/PeelRelease.wav",
 "0x17a9190b": "Global/HyperRing.wav",
 "0xdb54fcde": "Stage/Transform2.wav",
 "0xb17de250": "Global/MenuWoosh.wav",
 "0x7cf07353": "VO/Three.wav",
 "0xa5614411": "VO/Two.wav",
 "0x2ef5a4f9": "VO/One.wav",
 "0x2e45fa95": "VO/Go.wav",
 "0x7e80e5f8": "VO/Goal.wav",
 "0xb90a1d26": "VO/SonicWins.wav",
 "0x1e71df9d": "VO/TailsWins.wav",
 "0x6b8ec336": "VO/KnuxWins.wav",
 "0x629e3391": "Global/Push.wav",
 "0x92419562": "Stage/Fail.wav",
 "0xa37bccb0": "Stage/LedgeBreak.wav",
 "0x2d521478": "Stage/BossHit.wav",
 "0x6c2cc427": "Stage/Explosion2.wav",
 "0x42d25069": "Stage/Drop.wav",
 "0xb51b5b7b": "Stage/Flap.wav",
 "0x5c3ab595": "Stage/Splash.wav",
 "0xc8bfaee2": "Stage/Assemble.wav",
 "0xd71551b8": "Stage/Sharp.wav",
 "0x25538a99": "Stage/Rotate.wav",
 "0x886c20b0": "Stage/Impact2.wav",
 "0x8a1d0220": "Stage/Targeting1.wav",
 "0x8d154ef2": "Stage/Buzzsaw.wav",
 "0xb27fe944": "Stage/Button2.wav",
 "0x4954b74b": "Stage/HullClose.wav",
 "0x20b6338a": "Stage/Warning.wav",
 "0x96bffe80": "Stage/Drown.wav",
 "0x5ffa6bc9": "Special/Event.wav"
}